runeberg/__init__.py
runeberg/__main__.py
runeberg/article.py
runeberg/download.py
runeberg/lst_file.py
runeberg/page.py
runeberg/page_range.py
runeberg/person.py
runeberg/work.py
runeberg-0.0.2.dist-info/LICENSE
runeberg-0.0.2.dist-info/METADATA
runeberg-0.0.2.dist-info/WHEEL
runeberg-0.0.2.dist-info/entry_points.txt
runeberg-0.0.2.dist-info/top_level.txt
runeberg-0.0.2.dist-info/RECORD
