Metadata-Version: 2.1
Name: runeberg
Version: 0.0.2
Summary: Library for working with works from Projekt Runeberg (Runeberg.org).
Home-page: https://github.com/lokal-profil/runeberg
Author: André Costa
Author-email: lokal.profil@gmail.com
License: MIT
Keywords: runeberg,libraries,literature
Platform: UNKNOWN
Classifier: Programming Language :: Python :: 3
Classifier: Programming Language :: Python :: 3.6
Classifier: Programming Language :: Python :: 3.7
Classifier: License :: OSI Approved :: MIT License
Classifier: Operating System :: OS Independent
Requires-Dist: beautifulsoup4
Requires-Dist: html5lib
Requires-Dist: requests
Requires-Dist: tqdm
